{"nodes": [{"id": "d_shopify_theme_assets_quick_order_list_js", "label": "quick-order-list.js", "file_type": "code", "source_file": "D:\\Shopify-theme\\assets\\quick-order-list.js", "source_location": "L1"}, {"id": "quick_order_list_quickorderlistcomponent", "label": "QuickOrderListComponent", "file_type": "code", "source_file": "D:\\Shopify-theme\\assets\\quick-order-list.js", "source_location": "L21"}, {"id": "quick_order_list_quickorderlistcomponent_currentpage", "label": ".currentPage()", "file_type": "code", "source_file": "D:\\Shopify-theme\\assets\\quick-order-list.js", "source_location": "L48"}, {"id": "quick_order_list_quickorderlistcomponent_cartvariantids", "label": ".cartVariantIds()", "file_type": "code", "source_file": "D:\\Shopify-theme\\assets\\quick-order-list.js", "source_location": "L62"}, {"id": "quick_order_list_quickorderlistcomponent_connectedcallback", "label": ".connectedCallback()", "file_type": "code", "source_file": "D:\\Shopify-theme\\assets\\quick-order-list.js", "source_location": "L69"}, {"id": "quick_order_list_quickorderlistcomponent_disconnectedcallback", "label": ".disconnectedCallback()", "file_type": "code", "source_file": "D:\\Shopify-theme\\assets\\quick-order-list.js", "source_location": "L81"}, {"id": "quick_order_list_quickorderlistcomponent_isquantityinput", "label": ".#isQuantityInput()", "file_type": "code", "source_file": "D:\\Shopify-theme\\assets\\quick-order-list.js", "source_location": "L97"}, {"id": "quick_order_list_quickorderlistcomponent_scrolltocenter", "label": ".#scrollToCenter()", "file_type": "code", "source_file": "D:\\Shopify-theme\\assets\\quick-order-list.js", "source_location": "L151"}, {"id": "quick_order_list_quickorderlistcomponent_onpaginationcontrolclick", "label": ".onPaginationControlClick()", "file_type": "code", "source_file": "D:\\Shopify-theme\\assets\\quick-order-list.js", "source_location": "L163"}, {"id": "quick_order_list_quickorderlistcomponent_onlineitemremove", "label": ".onLineItemRemove()", "file_type": "code", "source_file": "D:\\Shopify-theme\\assets\\quick-order-list.js", "source_location": "L191"}, {"id": "quick_order_list_quickorderlistcomponent_onremoveall", "label": ".onRemoveAll()", "file_type": "code", "source_file": "D:\\Shopify-theme\\assets\\quick-order-list.js", "source_location": "L208"}, {"id": "quick_order_list_quickorderlistcomponent_handlequantityupdate", "label": ".#handleQuantityUpdate()", "file_type": "code", "source_file": "D:\\Shopify-theme\\assets\\quick-order-list.js", "source_location": "L280"}, {"id": "quick_order_list_quickorderlistcomponent_handlecartupdate", "label": ".#handleCartUpdate()", "file_type": "code", "source_file": "D:\\Shopify-theme\\assets\\quick-order-list.js", "source_location": "L376"}, {"id": "quick_order_list_quickorderlistcomponent_disablequickorderlistitems", "label": ".#disableQuickOrderListItems()", "file_type": "code", "source_file": "D:\\Shopify-theme\\assets\\quick-order-list.js", "source_location": "L405"}, {"id": "quick_order_list_quickorderlistcomponent_enablequickorderlistitems", "label": ".#enableQuickOrderListItems()", "file_type": "code", "source_file": "D:\\Shopify-theme\\assets\\quick-order-list.js", "source_location": "L409"}, {"id": "quick_order_list_quickorderlistcomponent_showremoveallconfirmation", "label": ".showRemoveAllConfirmation()", "file_type": "code", "source_file": "D:\\Shopify-theme\\assets\\quick-order-list.js", "source_location": "L417"}, {"id": "quick_order_list_quickorderlistcomponent_hideremoveallconfirmation", "label": ".hideRemoveAllConfirmation()", "file_type": "code", "source_file": "D:\\Shopify-theme\\assets\\quick-order-list.js", "source_location": "L427"}, {"id": "quick_order_list_quickorderlistcomponent_toggleconfirmationpanel", "label": ".#toggleConfirmationPanel()", "file_type": "code", "source_file": "D:\\Shopify-theme\\assets\\quick-order-list.js", "source_location": "L438"}, {"id": "quick_order_list_quickorderlistcomponent_showerrormessage", "label": ".#showErrorMessage()", "file_type": "code", "source_file": "D:\\Shopify-theme\\assets\\quick-order-list.js", "source_location": "L447"}, {"id": "quick_order_list_quickorderlistcomponent_clearerrormessage", "label": ".#clearErrorMessage()", "file_type": "code", "source_file": "D:\\Shopify-theme\\assets\\quick-order-list.js", "source_location": "L455"}, {"id": "quick_order_list_quickorderlistcomponent_showsuccessmessage", "label": ".#showSuccessMessage()", "file_type": "code", "source_file": "D:\\Shopify-theme\\assets\\quick-order-list.js", "source_location": "L463"}, {"id": "quick_order_list_quickorderlistcomponent_clearsuccessmessage", "label": ".#clearSuccessMessage()", "file_type": "code", "source_file": "D:\\Shopify-theme\\assets\\quick-order-list.js", "source_location": "L475"}, {"id": "quick_order_list_quickorderlistcomponent_applyshimmereffects", "label": ".#applyShimmerEffects()", "file_type": "code", "source_file": "D:\\Shopify-theme\\assets\\quick-order-list.js", "source_location": "L483"}, {"id": "quick_order_list_quickorderlistcomponent_scrolltotopofsection", "label": ".#scrollToTopOfSection()", "file_type": "code", "source_file": "D:\\Shopify-theme\\assets\\quick-order-list.js", "source_location": "L500"}, {"id": "quick_order_list_quickorderlistcomponent_focusfirstquantityinput", "label": ".#focusFirstQuantityInput()", "file_type": "code", "source_file": "D:\\Shopify-theme\\assets\\quick-order-list.js", "source_location": "L508"}, {"id": "quick_order_list_quickorderlistcomponent_updatesectionhtml", "label": ".#updateSectionHTML()", "file_type": "code", "source_file": "D:\\Shopify-theme\\assets\\quick-order-list.js", "source_location": "L521"}, {"id": "quick_order_list_quickorderlistcomponent_getsectionids", "label": ".#getSectionIds()", "file_type": "code", "source_file": "D:\\Shopify-theme\\assets\\quick-order-list.js", "source_location": "L534"}], "edges": [{"source": "d_shopify_theme_assets_quick_order_list_js", "target": "component", "relation": "imports_from", "confidence": "EXTRACTED", "source_file": "D:\\Shopify-theme\\assets\\quick-order-list.js", "source_location": "L1", "weight": 1.0}, {"source": "d_shopify_theme_assets_quick_order_list_js", "target": "events", "relation": "imports_from", "confidence": "EXTRACTED", "source_file": "D:\\Shopify-theme\\assets\\quick-order-list.js", "source_location": "L2", "weight": 1.0}, {"source": "d_shopify_theme_assets_quick_order_list_js", "target": "utilities", "relation": "imports_from", "confidence": "EXTRACTED", "source_file": "D:\\Shopify-theme\\assets\\quick-order-list.js", "source_location": "L3", "weight": 1.0}, {"source": "d_shopify_theme_assets_quick_order_list_js", "target": "section_renderer", "relation": "imports_from", "confidence": "EXTRACTED", "source_file": "D:\\Shopify-theme\\assets\\quick-order-list.js", "source_location": "L4", "weight": 1.0}, {"source": "d_shopify_theme_assets_quick_order_list_js", "target": "quick_order_list_quickorderlistcomponent", "relation": "contains", "confidence": "EXTRACTED", "source_file": "D:\\Shopify-theme\\assets\\quick-order-list.js", "source_location": "L21", "weight": 1.0}, {"source": "quick_order_list_quickorderlistcomponent", "target": "quick_order_list_quickorderlistcomponent_currentpage", "relation": "method", "confidence": "EXTRACTED", "source_file": "D:\\Shopify-theme\\assets\\quick-order-list.js", "source_location": "L48", "weight": 1.0}, {"source": "quick_order_list_quickorderlistcomponent", "target": "quick_order_list_quickorderlistcomponent_cartvariantids", "relation": "method", "confidence": "EXTRACTED", "source_file": "D:\\Shopify-theme\\assets\\quick-order-list.js", "source_location": "L62", "weight": 1.0}, {"source": "quick_order_list_quickorderlistcomponent", "target": "quick_order_list_quickorderlistcomponent_connectedcallback", "relation": "method", "confidence": "EXTRACTED", "source_file": "D:\\Shopify-theme\\assets\\quick-order-list.js", "source_location": "L69", "weight": 1.0}, {"source": "quick_order_list_quickorderlistcomponent", "target": "quick_order_list_quickorderlistcomponent_disconnectedcallback", "relation": "method", "confidence": "EXTRACTED", "source_file": "D:\\Shopify-theme\\assets\\quick-order-list.js", "source_location": "L81", "weight": 1.0}, {"source": "quick_order_list_quickorderlistcomponent", "target": "quick_order_list_quickorderlistcomponent_isquantityinput", "relation": "method", "confidence": "EXTRACTED", "source_file": "D:\\Shopify-theme\\assets\\quick-order-list.js", "source_location": "L97", "weight": 1.0}, {"source": "quick_order_list_quickorderlistcomponent", "target": "quick_order_list_quickorderlistcomponent_scrolltocenter", "relation": "method", "confidence": "EXTRACTED", "source_file": "D:\\Shopify-theme\\assets\\quick-order-list.js", "source_location": "L151", "weight": 1.0}, {"source": "quick_order_list_quickorderlistcomponent", "target": "quick_order_list_quickorderlistcomponent_onpaginationcontrolclick", "relation": "method", "confidence": "EXTRACTED", "source_file": "D:\\Shopify-theme\\assets\\quick-order-list.js", "source_location": "L163", "weight": 1.0}, {"source": "quick_order_list_quickorderlistcomponent", "target": "quick_order_list_quickorderlistcomponent_onlineitemremove", "relation": "method", "confidence": "EXTRACTED", "source_file": "D:\\Shopify-theme\\assets\\quick-order-list.js", "source_location": "L191", "weight": 1.0}, {"source": "quick_order_list_quickorderlistcomponent", "target": "quick_order_list_quickorderlistcomponent_onremoveall", "relation": "method", "confidence": "EXTRACTED", "source_file": "D:\\Shopify-theme\\assets\\quick-order-list.js", "source_location": "L208", "weight": 1.0}, {"source": "quick_order_list_quickorderlistcomponent", "target": "quick_order_list_quickorderlistcomponent_handlequantityupdate", "relation": "method", "confidence": "EXTRACTED", "source_file": "D:\\Shopify-theme\\assets\\quick-order-list.js", "source_location": "L280", "weight": 1.0}, {"source": "quick_order_list_quickorderlistcomponent", "target": "quick_order_list_quickorderlistcomponent_handlecartupdate", "relation": "method", "confidence": "EXTRACTED", "source_file": "D:\\Shopify-theme\\assets\\quick-order-list.js", "source_location": "L376", "weight": 1.0}, {"source": "quick_order_list_quickorderlistcomponent", "target": "quick_order_list_quickorderlistcomponent_disablequickorderlistitems", "relation": "method", "confidence": "EXTRACTED", "source_file": "D:\\Shopify-theme\\assets\\quick-order-list.js", "source_location": "L405", "weight": 1.0}, {"source": "quick_order_list_quickorderlistcomponent", "target": "quick_order_list_quickorderlistcomponent_enablequickorderlistitems", "relation": "method", "confidence": "EXTRACTED", "source_file": "D:\\Shopify-theme\\assets\\quick-order-list.js", "source_location": "L409", "weight": 1.0}, {"source": "quick_order_list_quickorderlistcomponent", "target": "quick_order_list_quickorderlistcomponent_showremoveallconfirmation", "relation": "method", "confidence": "EXTRACTED", "source_file": "D:\\Shopify-theme\\assets\\quick-order-list.js", "source_location": "L417", "weight": 1.0}, {"source": "quick_order_list_quickorderlistcomponent", "target": "quick_order_list_quickorderlistcomponent_hideremoveallconfirmation", "relation": "method", "confidence": "EXTRACTED", "source_file": "D:\\Shopify-theme\\assets\\quick-order-list.js", "source_location": "L427", "weight": 1.0}, {"source": "quick_order_list_quickorderlistcomponent", "target": "quick_order_list_quickorderlistcomponent_toggleconfirmationpanel", "relation": "method", "confidence": "EXTRACTED", "source_file": "D:\\Shopify-theme\\assets\\quick-order-list.js", "source_location": "L438", "weight": 1.0}, {"source": "quick_order_list_quickorderlistcomponent", "target": "quick_order_list_quickorderlistcomponent_showerrormessage", "relation": "method", "confidence": "EXTRACTED", "source_file": "D:\\Shopify-theme\\assets\\quick-order-list.js", "source_location": "L447", "weight": 1.0}, {"source": "quick_order_list_quickorderlistcomponent", "target": "quick_order_list_quickorderlistcomponent_clearerrormessage", "relation": "method", "confidence": "EXTRACTED", "source_file": "D:\\Shopify-theme\\assets\\quick-order-list.js", "source_location": "L455", "weight": 1.0}, {"source": "quick_order_list_quickorderlistcomponent", "target": "quick_order_list_quickorderlistcomponent_showsuccessmessage", "relation": "method", "confidence": "EXTRACTED", "source_file": "D:\\Shopify-theme\\assets\\quick-order-list.js", "source_location": "L463", "weight": 1.0}, {"source": "quick_order_list_quickorderlistcomponent", "target": "quick_order_list_quickorderlistcomponent_clearsuccessmessage", "relation": "method", "confidence": "EXTRACTED", "source_file": "D:\\Shopify-theme\\assets\\quick-order-list.js", "source_location": "L475", "weight": 1.0}, {"source": "quick_order_list_quickorderlistcomponent", "target": "quick_order_list_quickorderlistcomponent_applyshimmereffects", "relation": "method", "confidence": "EXTRACTED", "source_file": "D:\\Shopify-theme\\assets\\quick-order-list.js", "source_location": "L483", "weight": 1.0}, {"source": "quick_order_list_quickorderlistcomponent", "target": "quick_order_list_quickorderlistcomponent_scrolltotopofsection", "relation": "method", "confidence": "EXTRACTED", "source_file": "D:\\Shopify-theme\\assets\\quick-order-list.js", "source_location": "L500", "weight": 1.0}, {"source": "quick_order_list_quickorderlistcomponent", "target": "quick_order_list_quickorderlistcomponent_focusfirstquantityinput", "relation": "method", "confidence": "EXTRACTED", "source_file": "D:\\Shopify-theme\\assets\\quick-order-list.js", "source_location": "L508", "weight": 1.0}, {"source": "quick_order_list_quickorderlistcomponent", "target": "quick_order_list_quickorderlistcomponent_updatesectionhtml", "relation": "method", "confidence": "EXTRACTED", "source_file": "D:\\Shopify-theme\\assets\\quick-order-list.js", "source_location": "L521", "weight": 1.0}, {"source": "quick_order_list_quickorderlistcomponent", "target": "quick_order_list_quickorderlistcomponent_getsectionids", "relation": "method", "confidence": "EXTRACTED", "source_file": "D:\\Shopify-theme\\assets\\quick-order-list.js", "source_location": "L534", "weight": 1.0}, {"source": "quick_order_list_quickorderlistcomponent_onpaginationcontrolclick", "target": "quick_order_list_quickorderlistcomponent_scrolltotopofsection", "relation": "calls", "confidence": "EXTRACTED", "source_file": "D:\\Shopify-theme\\assets\\quick-order-list.js", "source_location": "L180", "weight": 1.0}, {"source": "quick_order_list_quickorderlistcomponent_onremoveall", "target": "quick_order_list_quickorderlistcomponent_clearsuccessmessage", "relation": "calls", "confidence": "EXTRACTED", "source_file": "D:\\Shopify-theme\\assets\\quick-order-list.js", "source_location": "L212", "weight": 1.0}, {"source": "quick_order_list_quickorderlistcomponent_onremoveall", "target": "quick_order_list_quickorderlistcomponent_clearerrormessage", "relation": "calls", "confidence": "EXTRACTED", "source_file": "D:\\Shopify-theme\\assets\\quick-order-list.js", "source_location": "L213", "weight": 1.0}, {"source": "quick_order_list_quickorderlistcomponent_onremoveall", "target": "quick_order_list_quickorderlistcomponent_applyshimmereffects", "relation": "calls", "confidence": "EXTRACTED", "source_file": "D:\\Shopify-theme\\assets\\quick-order-list.js", "source_location": "L214", "weight": 1.0}, {"source": "quick_order_list_quickorderlistcomponent_onremoveall", "target": "quick_order_list_quickorderlistcomponent_getsectionids", "relation": "calls", "confidence": "EXTRACTED", "source_file": "D:\\Shopify-theme\\assets\\quick-order-list.js", "source_location": "L234", "weight": 1.0}, {"source": "quick_order_list_quickorderlistcomponent_onremoveall", "target": "quick_order_list_quickorderlistcomponent_showerrormessage", "relation": "calls", "confidence": "EXTRACTED", "source_file": "D:\\Shopify-theme\\assets\\quick-order-list.js", "source_location": "L255", "weight": 1.0}, {"source": "quick_order_list_quickorderlistcomponent_onremoveall", "target": "quick_order_list_quickorderlistcomponent_updatesectionhtml", "relation": "calls", "confidence": "EXTRACTED", "source_file": "D:\\Shopify-theme\\assets\\quick-order-list.js", "source_location": "L257", "weight": 1.0}, {"source": "quick_order_list_quickorderlistcomponent_onremoveall", "target": "quick_order_list_quickorderlistcomponent_toggleconfirmationpanel", "relation": "calls", "confidence": "EXTRACTED", "source_file": "D:\\Shopify-theme\\assets\\quick-order-list.js", "source_location": "L258", "weight": 1.0}, {"source": "quick_order_list_quickorderlistcomponent_handlequantityupdate", "target": "quick_order_list_quickorderlistcomponent_clearsuccessmessage", "relation": "calls", "confidence": "EXTRACTED", "source_file": "D:\\Shopify-theme\\assets\\quick-order-list.js", "source_location": "L302", "weight": 1.0}, {"source": "quick_order_list_quickorderlistcomponent_handlequantityupdate", "target": "quick_order_list_quickorderlistcomponent_clearerrormessage", "relation": "calls", "confidence": "EXTRACTED", "source_file": "D:\\Shopify-theme\\assets\\quick-order-list.js", "source_location": "L303", "weight": 1.0}, {"source": "quick_order_list_quickorderlistcomponent_handlequantityupdate", "target": "quick_order_list_quickorderlistcomponent_applyshimmereffects", "relation": "calls", "confidence": "EXTRACTED", "source_file": "D:\\Shopify-theme\\assets\\quick-order-list.js", "source_location": "L309", "weight": 1.0}, {"source": "quick_order_list_quickorderlistcomponent_handlequantityupdate", "target": "quick_order_list_quickorderlistcomponent_disablequickorderlistitems", "relation": "calls", "confidence": "EXTRACTED", "source_file": "D:\\Shopify-theme\\assets\\quick-order-list.js", "source_location": "L311", "weight": 1.0}, {"source": "quick_order_list_quickorderlistcomponent_handlequantityupdate", "target": "quick_order_list_quickorderlistcomponent_getsectionids", "relation": "calls", "confidence": "EXTRACTED", "source_file": "D:\\Shopify-theme\\assets\\quick-order-list.js", "source_location": "L326", "weight": 1.0}, {"source": "quick_order_list_quickorderlistcomponent_handlequantityupdate", "target": "quick_order_list_quickorderlistcomponent_showerrormessage", "relation": "calls", "confidence": "EXTRACTED", "source_file": "D:\\Shopify-theme\\assets\\quick-order-list.js", "source_location": "L341", "weight": 1.0}, {"source": "quick_order_list_quickorderlistcomponent_handlequantityupdate", "target": "quick_order_list_quickorderlistcomponent_updatesectionhtml", "relation": "calls", "confidence": "EXTRACTED", "source_file": "D:\\Shopify-theme\\assets\\quick-order-list.js", "source_location": "L348", "weight": 1.0}, {"source": "quick_order_list_quickorderlistcomponent_handlequantityupdate", "target": "quick_order_list_quickorderlistcomponent_showsuccessmessage", "relation": "calls", "confidence": "EXTRACTED", "source_file": "D:\\Shopify-theme\\assets\\quick-order-list.js", "source_location": "L352", "weight": 1.0}, {"source": "quick_order_list_quickorderlistcomponent_handlequantityupdate", "target": "quick_order_list_quickorderlistcomponent_enablequickorderlistitems", "relation": "calls", "confidence": "EXTRACTED", "source_file": "D:\\Shopify-theme\\assets\\quick-order-list.js", "source_location": "L365", "weight": 1.0}, {"source": "quick_order_list_quickorderlistcomponent_handlecartupdate", "target": "quick_order_list_quickorderlistcomponent_enablequickorderlistitems", "relation": "calls", "confidence": "EXTRACTED", "source_file": "D:\\Shopify-theme\\assets\\quick-order-list.js", "source_location": "L383", "weight": 1.0}, {"source": "quick_order_list_quickorderlistcomponent_handlecartupdate", "target": "quick_order_list_quickorderlistcomponent_updatesectionhtml", "relation": "calls", "confidence": "EXTRACTED", "source_file": "D:\\Shopify-theme\\assets\\quick-order-list.js", "source_location": "L388", "weight": 1.0}, {"source": "quick_order_list_quickorderlistcomponent_showremoveallconfirmation", "target": "quick_order_list_quickorderlistcomponent_toggleconfirmationpanel", "relation": "calls", "confidence": "EXTRACTED", "source_file": "D:\\Shopify-theme\\assets\\quick-order-list.js", "source_location": "L420", "weight": 1.0}, {"source": "quick_order_list_quickorderlistcomponent_hideremoveallconfirmation", "target": "quick_order_list_quickorderlistcomponent_toggleconfirmationpanel", "relation": "calls", "confidence": "EXTRACTED", "source_file": "D:\\Shopify-theme\\assets\\quick-order-list.js", "source_location": "L429", "weight": 1.0}, {"source": "quick_order_list_quickorderlistcomponent_showsuccessmessage", "target": "quick_order_list_quickorderlistcomponent_clearerrormessage", "relation": "calls", "confidence": "EXTRACTED", "source_file": "D:\\Shopify-theme\\assets\\quick-order-list.js", "source_location": "L464", "weight": 1.0}], "raw_calls": [{"caller_nid": "quick_order_list_quickorderlistcomponent_currentpage", "callee": "parseInt", "source_file": "D:\\Shopify-theme\\assets\\quick-order-list.js", "source_location": "L50"}, {"caller_nid": "quick_order_list_quickorderlistcomponent_currentpage", "callee": "isNaN", "source_file": "D:\\Shopify-theme\\assets\\quick-order-list.js", "source_location": "L51"}, {"caller_nid": "quick_order_list_quickorderlistcomponent_cartvariantids", "callee": "parse", "source_file": "D:\\Shopify-theme\\assets\\quick-order-list.js", "source_location": "L66"}, {"caller_nid": "quick_order_list_quickorderlistcomponent_connectedcallback", "callee": "debounce", "source_file": "D:\\Shopify-theme\\assets\\quick-order-list.js", "source_location": "L72"}, {"caller_nid": "quick_order_list_quickorderlistcomponent_connectedcallback", "callee": "bind", "source_file": "D:\\Shopify-theme\\assets\\quick-order-list.js", "source_location": "L72"}, {"caller_nid": "quick_order_list_quickorderlistcomponent_connectedcallback", "callee": "bind", "source_file": "D:\\Shopify-theme\\assets\\quick-order-list.js", "source_location": "L73"}, {"caller_nid": "quick_order_list_quickorderlistcomponent_connectedcallback", "callee": "addEventListener", "source_file": "D:\\Shopify-theme\\assets\\quick-order-list.js", "source_location": "L75"}, {"caller_nid": "quick_order_list_quickorderlistcomponent_connectedcallback", "callee": "addEventListener", "source_file": "D:\\Shopify-theme\\assets\\quick-order-list.js", "source_location": "L76"}, {"caller_nid": "quick_order_list_quickorderlistcomponent_connectedcallback", "callee": "addEventListener", "source_file": "D:\\Shopify-theme\\assets\\quick-order-list.js", "source_location": "L77"}, {"caller_nid": "quick_order_list_quickorderlistcomponent_connectedcallback", "callee": "addEventListener", "source_file": "D:\\Shopify-theme\\assets\\quick-order-list.js", "source_location": "L78"}, {"caller_nid": "quick_order_list_quickorderlistcomponent_disconnectedcallback", "callee": "removeEventListener", "source_file": "D:\\Shopify-theme\\assets\\quick-order-list.js", "source_location": "L84"}, {"caller_nid": "quick_order_list_quickorderlistcomponent_disconnectedcallback", "callee": "removeEventListener", "source_file": "D:\\Shopify-theme\\assets\\quick-order-list.js", "source_location": "L85"}, {"caller_nid": "quick_order_list_quickorderlistcomponent_disconnectedcallback", "callee": "removeEventListener", "source_file": "D:\\Shopify-theme\\assets\\quick-order-list.js", "source_location": "L86"}, {"caller_nid": "quick_order_list_quickorderlistcomponent_disconnectedcallback", "callee": "removeEventListener", "source_file": "D:\\Shopify-theme\\assets\\quick-order-list.js", "source_location": "L87"}, {"caller_nid": "quick_order_list_quickorderlistcomponent_disconnectedcallback", "callee": "abort", "source_file": "D:\\Shopify-theme\\assets\\quick-order-list.js", "source_location": "L89"}, {"caller_nid": "quick_order_list_quickorderlistcomponent_isquantityinput", "callee": "matches", "source_file": "D:\\Shopify-theme\\assets\\quick-order-list.js", "source_location": "L98"}, {"caller_nid": "quick_order_list_quickorderlistcomponent_scrolltocenter", "callee": "scrollIntoView", "source_file": "D:\\Shopify-theme\\assets\\quick-order-list.js", "source_location": "L152"}, {"caller_nid": "quick_order_list_quickorderlistcomponent_onpaginationcontrolclick", "callee": "preventDefault", "source_file": "D:\\Shopify-theme\\assets\\quick-order-list.js", "source_location": "L164"}, {"caller_nid": "quick_order_list_quickorderlistcomponent_onpaginationcontrolclick", "callee": "abort", "source_file": "D:\\Shopify-theme\\assets\\quick-order-list.js", "source_location": "L169"}, {"caller_nid": "quick_order_list_quickorderlistcomponent_onpaginationcontrolclick", "callee": "entries", "source_file": "D:\\Shopify-theme\\assets\\quick-order-list.js", "source_location": "L173"}, {"caller_nid": "quick_order_list_quickorderlistcomponent_onpaginationcontrolclick", "callee": "set", "source_file": "D:\\Shopify-theme\\assets\\quick-order-list.js", "source_location": "L174"}, {"caller_nid": "quick_order_list_quickorderlistcomponent_onpaginationcontrolclick", "callee": "renderSection", "source_file": "D:\\Shopify-theme\\assets\\quick-order-list.js", "source_location": "L177"}, {"caller_nid": "quick_order_list_quickorderlistcomponent_onpaginationcontrolclick", "callee": "requestAnimationFrame", "source_file": "D:\\Shopify-theme\\assets\\quick-order-list.js", "source_location": "L183"}, {"caller_nid": "quick_order_list_quickorderlistcomponent_onlineitemremove", "callee": "preventDefault", "source_file": "D:\\Shopify-theme\\assets\\quick-order-list.js", "source_location": "L192"}, {"caller_nid": "quick_order_list_quickorderlistcomponent_onlineitemremove", "callee": "find", "source_file": "D:\\Shopify-theme\\assets\\quick-order-list.js", "source_location": "L194"}, {"caller_nid": "quick_order_list_quickorderlistcomponent_onlineitemremove", "callee": "querySelector", "source_file": "D:\\Shopify-theme\\assets\\quick-order-list.js", "source_location": "L197"}, {"caller_nid": "quick_order_list_quickorderlistcomponent_onlineitemremove", "callee": "dispatchEvent", "source_file": "D:\\Shopify-theme\\assets\\quick-order-list.js", "source_location": "L200"}, {"caller_nid": "quick_order_list_quickorderlistcomponent_onlineitemremove", "callee": "Number", "source_file": "D:\\Shopify-theme\\assets\\quick-order-list.js", "source_location": "L200"}, {"caller_nid": "quick_order_list_quickorderlistcomponent_onremoveall", "callee": "preventDefault", "source_file": "D:\\Shopify-theme\\assets\\quick-order-list.js", "source_location": "L209"}, {"caller_nid": "quick_order_list_quickorderlistcomponent_onremoveall", "callee": "abort", "source_file": "D:\\Shopify-theme\\assets\\quick-order-list.js", "source_location": "L216"}, {"caller_nid": "quick_order_list_quickorderlistcomponent_onremoveall", "callee": "String", "source_file": "D:\\Shopify-theme\\assets\\quick-order-list.js", "source_location": "L225"}, {"caller_nid": "quick_order_list_quickorderlistcomponent_onremoveall", "callee": "keys", "source_file": "D:\\Shopify-theme\\assets\\quick-order-list.js", "source_location": "L229"}, {"caller_nid": "quick_order_list_quickorderlistcomponent_onremoveall", "callee": "resetShimmer", "source_file": "D:\\Shopify-theme\\assets\\quick-order-list.js", "source_location": "L230"}, {"caller_nid": "quick_order_list_quickorderlistcomponent_onremoveall", "callee": "set", "source_file": "D:\\Shopify-theme\\assets\\quick-order-list.js", "source_location": "L236"}, {"caller_nid": "quick_order_list_quickorderlistcomponent_onremoveall", "callee": "toString", "source_file": "D:\\Shopify-theme\\assets\\quick-order-list.js", "source_location": "L236"}, {"caller_nid": "quick_order_list_quickorderlistcomponent_onremoveall", "callee": "stringify", "source_file": "D:\\Shopify-theme\\assets\\quick-order-list.js", "source_location": "L238"}, {"caller_nid": "quick_order_list_quickorderlistcomponent_onremoveall", "callee": "join", "source_file": "D:\\Shopify-theme\\assets\\quick-order-list.js", "source_location": "L240"}, {"caller_nid": "quick_order_list_quickorderlistcomponent_onremoveall", "callee": "fetch", "source_file": "D:\\Shopify-theme\\assets\\quick-order-list.js", "source_location": "L244"}, {"caller_nid": "quick_order_list_quickorderlistcomponent_onremoveall", "callee": "fetchConfig", "source_file": "D:\\Shopify-theme\\assets\\quick-order-list.js", "source_location": "L245"}, {"caller_nid": "quick_order_list_quickorderlistcomponent_onremoveall", "callee": "text", "source_file": "D:\\Shopify-theme\\assets\\quick-order-list.js", "source_location": "L249"}, {"caller_nid": "quick_order_list_quickorderlistcomponent_onremoveall", "callee": "parse", "source_file": "D:\\Shopify-theme\\assets\\quick-order-list.js", "source_location": "L250"}, {"caller_nid": "quick_order_list_quickorderlistcomponent_onremoveall", "callee": "resetShimmer", "source_file": "D:\\Shopify-theme\\assets\\quick-order-list.js", "source_location": "L252"}, {"caller_nid": "quick_order_list_quickorderlistcomponent_onremoveall", "callee": "dispatchEvent", "source_file": "D:\\Shopify-theme\\assets\\quick-order-list.js", "source_location": "L261"}, {"caller_nid": "quick_order_list_quickorderlistcomponent_onremoveall", "callee": "resetShimmer", "source_file": "D:\\Shopify-theme\\assets\\quick-order-list.js", "source_location": "L270"}, {"caller_nid": "quick_order_list_quickorderlistcomponent_handlequantityupdate", "callee": "contains", "source_file": "D:\\Shopify-theme\\assets\\quick-order-list.js", "source_location": "L284"}, {"caller_nid": "quick_order_list_quickorderlistcomponent_handlequantityupdate", "callee": "find", "source_file": "D:\\Shopify-theme\\assets\\quick-order-list.js", "source_location": "L290"}, {"caller_nid": "quick_order_list_quickorderlistcomponent_handlequantityupdate", "callee": "querySelector", "source_file": "D:\\Shopify-theme\\assets\\quick-order-list.js", "source_location": "L299"}, {"caller_nid": "quick_order_list_quickorderlistcomponent_handlequantityupdate", "callee": "parseInt", "source_file": "D:\\Shopify-theme\\assets\\quick-order-list.js", "source_location": "L300"}, {"caller_nid": "quick_order_list_quickorderlistcomponent_handlequantityupdate", "callee": "abort", "source_file": "D:\\Shopify-theme\\assets\\quick-order-list.js", "source_location": "L312"}, {"caller_nid": "quick_order_list_quickorderlistcomponent_handlequantityupdate", "callee": "set", "source_file": "D:\\Shopify-theme\\assets\\quick-order-list.js", "source_location": "L322"}, {"caller_nid": "quick_order_list_quickorderlistcomponent_handlequantityupdate", "callee": "toString", "source_file": "D:\\Shopify-theme\\assets\\quick-order-list.js", "source_location": "L322"}, {"caller_nid": "quick_order_list_quickorderlistcomponent_handlequantityupdate", "callee": "stringify", "source_file": "D:\\Shopify-theme\\assets\\quick-order-list.js", "source_location": "L324"}, {"caller_nid": "quick_order_list_quickorderlistcomponent_handlequantityupdate", "callee": "join", "source_file": "D:\\Shopify-theme\\assets\\quick-order-list.js", "source_location": "L326"}, {"caller_nid": "quick_order_list_quickorderlistcomponent_handlequantityupdate", "callee": "fetch", "source_file": "D:\\Shopify-theme\\assets\\quick-order-list.js", "source_location": "L330"}, {"caller_nid": "quick_order_list_quickorderlistcomponent_handlequantityupdate", "callee": "fetchConfig", "source_file": "D:\\Shopify-theme\\assets\\quick-order-list.js", "source_location": "L331"}, {"caller_nid": "quick_order_list_quickorderlistcomponent_handlequantityupdate", "callee": "text", "source_file": "D:\\Shopify-theme\\assets\\quick-order-list.js", "source_location": "L335"}, {"caller_nid": "quick_order_list_quickorderlistcomponent_handlequantityupdate", "callee": "parse", "source_file": "D:\\Shopify-theme\\assets\\quick-order-list.js", "source_location": "L336"}, {"caller_nid": "quick_order_list_quickorderlistcomponent_handlequantityupdate", "callee": "resetShimmer", "source_file": "D:\\Shopify-theme\\assets\\quick-order-list.js", "source_location": "L338"}, {"caller_nid": "quick_order_list_quickorderlistcomponent_handlequantityupdate", "callee": "set", "source_file": "D:\\Shopify-theme\\assets\\quick-order-list.js", "source_location": "L344"}, {"caller_nid": "quick_order_list_quickorderlistcomponent_handlequantityupdate", "callee": "toString", "source_file": "D:\\Shopify-theme\\assets\\quick-order-list.js", "source_location": "L344"}, {"caller_nid": "quick_order_list_quickorderlistcomponent_handlequantityupdate", "callee": "renderSection", "source_file": "D:\\Shopify-theme\\assets\\quick-order-list.js", "source_location": "L345"}, {"caller_nid": "quick_order_list_quickorderlistcomponent_handlequantityupdate", "callee": "dispatchEvent", "source_file": "D:\\Shopify-theme\\assets\\quick-order-list.js", "source_location": "L355"}, {"caller_nid": "quick_order_list_quickorderlistcomponent_handlequantityupdate", "callee": "resetShimmer", "source_file": "D:\\Shopify-theme\\assets\\quick-order-list.js", "source_location": "L366"}, {"caller_nid": "quick_order_list_quickorderlistcomponent_handlecartupdate", "callee": "abort", "source_file": "D:\\Shopify-theme\\assets\\quick-order-list.js", "source_location": "L384"}, {"caller_nid": "quick_order_list_quickorderlistcomponent_handlecartupdate", "callee": "set", "source_file": "D:\\Shopify-theme\\assets\\quick-order-list.js", "source_location": "L396"}, {"caller_nid": "quick_order_list_quickorderlistcomponent_handlecartupdate", "callee": "toString", "source_file": "D:\\Shopify-theme\\assets\\quick-order-list.js", "source_location": "L396"}, {"caller_nid": "quick_order_list_quickorderlistcomponent_handlecartupdate", "callee": "renderSection", "source_file": "D:\\Shopify-theme\\assets\\quick-order-list.js", "source_location": "L398"}, {"caller_nid": "quick_order_list_quickorderlistcomponent_disablequickorderlistitems", "callee": "add", "source_file": "D:\\Shopify-theme\\assets\\quick-order-list.js", "source_location": "L406"}, {"caller_nid": "quick_order_list_quickorderlistcomponent_enablequickorderlistitems", "callee": "remove", "source_file": "D:\\Shopify-theme\\assets\\quick-order-list.js", "source_location": "L410"}, {"caller_nid": "quick_order_list_quickorderlistcomponent_showremoveallconfirmation", "callee": "preventDefault", "source_file": "D:\\Shopify-theme\\assets\\quick-order-list.js", "source_location": "L418"}, {"caller_nid": "quick_order_list_quickorderlistcomponent_hideremoveallconfirmation", "callee": "preventDefault", "source_file": "D:\\Shopify-theme\\assets\\quick-order-list.js", "source_location": "L428"}, {"caller_nid": "quick_order_list_quickorderlistcomponent_hideremoveallconfirmation", "callee": "focus", "source_file": "D:\\Shopify-theme\\assets\\quick-order-list.js", "source_location": "L430"}, {"caller_nid": "quick_order_list_quickorderlistcomponent_toggleconfirmationpanel", "callee": "toggle", "source_file": "D:\\Shopify-theme\\assets\\quick-order-list.js", "source_location": "L439"}, {"caller_nid": "quick_order_list_quickorderlistcomponent_toggleconfirmationpanel", "callee": "toggle", "source_file": "D:\\Shopify-theme\\assets\\quick-order-list.js", "source_location": "L440"}, {"caller_nid": "quick_order_list_quickorderlistcomponent_showerrormessage", "callee": "remove", "source_file": "D:\\Shopify-theme\\assets\\quick-order-list.js", "source_location": "L449"}, {"caller_nid": "quick_order_list_quickorderlistcomponent_clearerrormessage", "callee": "add", "source_file": "D:\\Shopify-theme\\assets\\quick-order-list.js", "source_location": "L456"}, {"caller_nid": "quick_order_list_quickorderlistcomponent_showsuccessmessage", "callee": "replace", "source_file": "D:\\Shopify-theme\\assets\\quick-order-list.js", "source_location": "L469"}, {"caller_nid": "quick_order_list_quickorderlistcomponent_showsuccessmessage", "callee": "toString", "source_file": "D:\\Shopify-theme\\assets\\quick-order-list.js", "source_location": "L469"}, {"caller_nid": "quick_order_list_quickorderlistcomponent_showsuccessmessage", "callee": "remove", "source_file": "D:\\Shopify-theme\\assets\\quick-order-list.js", "source_location": "L472"}, {"caller_nid": "quick_order_list_quickorderlistcomponent_clearsuccessmessage", "callee": "add", "source_file": "D:\\Shopify-theme\\assets\\quick-order-list.js", "source_location": "L476"}, {"caller_nid": "quick_order_list_quickorderlistcomponent_applyshimmereffects", "callee": "find", "source_file": "D:\\Shopify-theme\\assets\\quick-order-list.js", "source_location": "L485"}, {"caller_nid": "quick_order_list_quickorderlistcomponent_applyshimmereffects", "callee": "querySelector", "source_file": "D:\\Shopify-theme\\assets\\quick-order-list.js", "source_location": "L488"}, {"caller_nid": "quick_order_list_quickorderlistcomponent_applyshimmereffects", "callee": "shimmer", "source_file": "D:\\Shopify-theme\\assets\\quick-order-list.js", "source_location": "L490"}, {"caller_nid": "quick_order_list_quickorderlistcomponent_applyshimmereffects", "callee": "querySelector", "source_file": "D:\\Shopify-theme\\assets\\quick-order-list.js", "source_location": "L495"}, {"caller_nid": "quick_order_list_quickorderlistcomponent_applyshimmereffects", "callee": "shimmer", "source_file": "D:\\Shopify-theme\\assets\\quick-order-list.js", "source_location": "L497"}, {"caller_nid": "quick_order_list_quickorderlistcomponent_scrolltotopofsection", "callee": "requestAnimationFrame", "source_file": "D:\\Shopify-theme\\assets\\quick-order-list.js", "source_location": "L502"}, {"caller_nid": "quick_order_list_quickorderlistcomponent_focusfirstquantityinput", "callee": "querySelectorAll", "source_file": "D:\\Shopify-theme\\assets\\quick-order-list.js", "source_location": "L509"}, {"caller_nid": "quick_order_list_quickorderlistcomponent_focusfirstquantityinput", "callee": "focus", "source_file": "D:\\Shopify-theme\\assets\\quick-order-list.js", "source_location": "L511"}, {"caller_nid": "quick_order_list_quickorderlistcomponent_updatesectionhtml", "callee": "morphSection", "source_file": "D:\\Shopify-theme\\assets\\quick-order-list.js", "source_location": "L525"}, {"caller_nid": "quick_order_list_quickorderlistcomponent_getsectionids", "callee": "push", "source_file": "D:\\Shopify-theme\\assets\\quick-order-list.js", "source_location": "L538"}, {"caller_nid": "quick_order_list_quickorderlistcomponent_getsectionids", "callee": "querySelectorAll", "source_file": "D:\\Shopify-theme\\assets\\quick-order-list.js", "source_location": "L542"}, {"caller_nid": "quick_order_list_quickorderlistcomponent_getsectionids", "callee": "includes", "source_file": "D:\\Shopify-theme\\assets\\quick-order-list.js", "source_location": "L545"}, {"caller_nid": "quick_order_list_quickorderlistcomponent_getsectionids", "callee": "push", "source_file": "D:\\Shopify-theme\\assets\\quick-order-list.js", "source_location": "L546"}]}